chaoscf/__init__.py
chaoscf/actions.py
chaoscf/api.py
chaoscf/probes.py
chaostoolkit_cloud_foundry-0.7.3.dist-info/LICENSE
chaostoolkit_cloud_foundry-0.7.3.dist-info/METADATA
chaostoolkit_cloud_foundry-0.7.3.dist-info/WHEEL
chaostoolkit_cloud_foundry-0.7.3.dist-info/top_level.txt
chaostoolkit_cloud_foundry-0.7.3.dist-info/RECORD
